makerpack/__init__.py
makerpack/addr.py
makerpack/buzzer.py
makerpack/dht.py
makerpack/driver.py
makerpack/encoder.py
makerpack/lcd.py
makerpack/pico.py
makerpack/rtc.py
makerpack/ultrasound.py
makerpack-0.1.0.dist-info/METADATA
makerpack-0.1.0.dist-info/WHEEL
makerpack-0.1.0.dist-info/top_level.txt
makerpack-0.1.0.dist-info/RECORD
